MANIFEST.in
README.md
setup.py
luckdog/__init__.py
luckdog/__version__.py
luckdog/box.py
luckdog/main.py
luckdog.egg-info/PKG-INFO
luckdog.egg-info/SOURCES.txt
luckdog.egg-info/dependency_links.txt
luckdog.egg-info/requires.txt
luckdog.egg-info/top_level.txt
luckdog.egg-info/zip-safe
luckdog/__pycache__/__init__.cpython-310.pyc
luckdog/__pycache__/__version__.cpython-310.pyc
luckdog/__pycache__/box.cpython-310.pyc
luckdog/box/net.py
luckdog/net/__init__.py
luckdog/net/emnu.py
luckdog/net/http.py
luckdog/net/__pycache__/__init__.cpython-310.pyc
luckdog/net/__pycache__/emnu.cpython-310.pyc
luckdog/net/__pycache__/http.cpython-310.pyc
luckdog/test/__init__.py
luckdog/test/report.py
luckdog/test/suite.py
luckdog/test/tool.py
luckdog/utils/__init__.py
luckdog/utils/cmd.py
luckdog/utils/code.py
luckdog/utils/eg.py
luckdog/utils/encrypt.py
luckdog/utils/form.py
luckdog/utils/master-private.pem
luckdog/utils/master-public.pem
luckdog/utils/ss.py
luckdog/utils/tools.py
luckdog/utils/__pycache__/__init__.cpython-310.pyc
luckdog/utils/__pycache__/tools.cpython-310.pyc