Metadata-Version: 2.1
Name: luckdog
Version: 1.2.9
Summary: a light-minded faceman,like postman.
Home-page: https://pypi.org/project/luckdog/#description
Author: goblinintree
Author-email: goblinintree@126.com
License: MIT
Keywords: postman,faceman,test
Platform: all
Classifier: Environment :: Web Environment
Classifier: License :: OSI Approved :: MIT License
Classifier: Operating System :: Microsoft
Classifier: Programming Language :: Python :: 3.7
